{
  "problem": "C1DTLZ1",
  "m": 15,
  "algorithm": "C-MOEA/DD",
  "igd_median": 0.14806001774011635,
  "igd_iqr": 0.015995482491807378,
  "hv_median": 4.1677585299823665,
  "hv_iqr": 0.015017177814654836,
  "n_runs_feasible": 51,
  "n_runs_total": 51,
  "runs": [
    {
      "run_idx": 5,
      "igd": 0.15537079114505986,
      "hv": 4.167924313989945,
      "n_feasible": 135,
      "time_sec": 966.9693803787231
    },
    {
      "run_idx": 6,
      "igd": 0.1271081215213096,
      "hv": 4.148834996228801,
      "n_feasible": 135,
      "time_sec": 1003.2411942481995
    },
    {
      "run_idx": 1,
      "igd": 0.15105401210098457,
      "hv": 4.17479024384667,
      "n_feasible": 135,
      "time_sec": 1011.9917385578156
    },
    {
      "run_idx": 9,
      "igd": 0.13954779920225685,
      "hv": 4.173553853993144,
      "n_feasible": 135,
      "time_sec": 1016.7061660289764
    },
    {
      "run_idx": 10,
      "igd": 0.1497865318062181,
      "hv": 4.173821393339422,
      "n_feasible": 135,
      "time_sec": 1062.1335911750793
    },
    {
      "run_idx": 12,
      "igd": 0.15059406793315555,
      "hv": 4.160714620659589,
      "n_feasible": 135,
      "time_sec": 1069.4066712856293
    },
    {
      "run_idx": 4,
      "igd": 0.15387588468831842,
      "hv": 4.175123130994121,
      "n_feasible": 135,
      "time_sec": 1071.6685466766357
    },
    {
      "run_idx": 8,
      "igd": 0.12714880701546658,
      "hv": 4.1635297958485324,
      "n_feasible": 135,
      "time_sec": 1103.3553647994995
    },
    {
      "run_idx": 13,
      "igd": 0.214620294613413,
      "hv": 4.157937977387815,
      "n_feasible": 135,
      "time_sec": 1139.0876502990723
    },
    {
      "run_idx": 7,
      "igd": 0.14372639547332472,
      "hv": 4.1688023301818244,
      "n_feasible": 135,
      "time_sec": 1171.883908033371
    },
    {
      "run_idx": 11,
      "igd": 0.13605742347844174,
      "hv": 4.157015531118125,
      "n_feasible": 135,
      "time_sec": 1210.4226083755493
    },
    {
      "run_idx": 0,
      "igd": 0.1580008491832393,
      "hv": 4.156573315837016,
      "n_feasible": 135,
      "time_sec": 1254.2373688220978
    },
    {
      "run_idx": 3,
      "igd": 0.1513991051751344,
      "hv": 4.171602866677191,
      "n_feasible": 135,
      "time_sec": 1263.1082944869995
    },
    {
      "run_idx": 2,
      "igd": 0.15022466759339798,
      "hv": 4.167229655061357,
      "n_feasible": 135,
      "time_sec": 1312.3430604934692
    },
    {
      "run_idx": 17,
      "igd": 0.13332885882120454,
      "hv": 4.1747263364104255,
      "n_feasible": 135,
      "time_sec": 854.1075246334076
    },
    {
      "run_idx": 15,
      "igd": 0.13738592464030008,
      "hv": 4.155387702854986,
      "n_feasible": 135,
      "time_sec": 880.8225452899933
    },
    {
      "run_idx": 19,
      "igd": 0.13685184759914806,
      "hv": 4.1742376429295565,
      "n_feasible": 135,
      "time_sec": 1009.537956237793
    },
    {
      "run_idx": 14,
      "igd": 0.15945539741312803,
      "hv": 4.164747565012848,
      "n_feasible": 135,
      "time_sec": 1119.457285642624
    },
    {
      "run_idx": 21,
      "igd": 0.13405263777925938,
      "hv": 4.131004859161014,
      "n_feasible": 135,
      "time_sec": 997.0133566856384
    },
    {
      "run_idx": 22,
      "igd": 0.14374825806628927,
      "hv": 4.175248126880494,
      "n_feasible": 135,
      "time_sec": 973.3302581310272
    },
    {
      "run_idx": 16,
      "igd": 0.13019280299984645,
      "hv": 4.1655984775309784,
      "n_feasible": 135,
      "time_sec": 1108.608077287674
    },
    {
      "run_idx": 20,
      "igd": 0.15279836329774657,
      "hv": 4.170638282602995,
      "n_feasible": 135,
      "time_sec": 1050.6672856807709
    },
    {
      "run_idx": 25,
      "igd": 0.13841442303186569,
      "hv": 4.157334637523443,
      "n_feasible": 135,
      "time_sec": 883.5076134204865
    },
    {
      "run_idx": 23,
      "igd": 0.1498112669269765,
      "hv": 4.165067139492101,
      "n_feasible": 135,
      "time_sec": 983.8008985519409
    },
    {
      "run_idx": 18,
      "igd": 0.15723890230607257,
      "hv": 4.169062481894467,
      "n_feasible": 135,
      "time_sec": 1226.6050312519073
    },
    {
      "run_idx": 24,
      "igd": 0.1395317115649218,
      "hv": 4.120152629939121,
      "n_feasible": 135,
      "time_sec": 1142.163318157196
    },
    {
      "run_idx": 26,
      "igd": 0.14806001774011635,
      "hv": 4.16821930607225,
      "n_feasible": 135,
      "time_sec": 1213.2513875961304
    },
    {
      "run_idx": 27,
      "igd": 0.12371183383298225,
      "hv": 4.173669036727121,
      "n_feasible": 135,
      "time_sec": 1292.9506576061249
    },
    {
      "run_idx": 29,
      "igd": 0.12451101451712972,
      "hv": 4.157135455913859,
      "n_feasible": 135,
      "time_sec": 1162.9612629413605
    },
    {
      "run_idx": 31,
      "igd": 0.12364550174423324,
      "hv": 4.168491974357235,
      "n_feasible": 135,
      "time_sec": 1116.0060913562775
    },
    {
      "run_idx": 28,
      "igd": 0.1612094545790727,
      "hv": 4.157035947992267,
      "n_feasible": 135,
      "time_sec": 1349.4174506664276
    },
    {
      "run_idx": 30,
      "igd": 0.14129655218293954,
      "hv": 4.167638001219648,
      "n_feasible": 135,
      "time_sec": 1244.1564328670502
    },
    {
      "run_idx": 33,
      "igd": 0.1666118886666638,
      "hv": 4.167622197079577,
      "n_feasible": 135,
      "time_sec": 1215.250452041626
    },
    {
      "run_idx": 32,
      "igd": 0.13926318767233375,
      "hv": 4.162438179355218,
      "n_feasible": 135,
      "time_sec": 1237.3839943408966
    },
    {
      "run_idx": 37,
      "igd": 0.12325885086779632,
      "hv": 4.171711838974211,
      "n_feasible": 135,
      "time_sec": 1208.9739773273468
    },
    {
      "run_idx": 35,
      "igd": 0.15849726470149747,
      "hv": 4.17295951615877,
      "n_feasible": 135,
      "time_sec": 1281.9167869091034
    },
    {
      "run_idx": 36,
      "igd": 0.1655474590059262,
      "hv": 4.170788279887994,
      "n_feasible": 135,
      "time_sec": 1290.5031390190125
    },
    {
      "run_idx": 34,
      "igd": 0.13074751100872664,
      "hv": 4.1677585299823665,
      "n_feasible": 135,
      "time_sec": 1325.9008095264435
    },
    {
      "run_idx": 38,
      "igd": 0.14832443760073175,
      "hv": 4.174130146882501,
      "n_feasible": 135,
      "time_sec": 1340.524083852768
    },
    {
      "run_idx": 39,
      "igd": 0.15391542796746213,
      "hv": 4.171374015627088,
      "n_feasible": 135,
      "time_sec": 1289.4488506317139
    },
    {
      "run_idx": 41,
      "igd": 0.14737020388345393,
      "hv": 4.171472595889299,
      "n_feasible": 135,
      "time_sec": 1153.3198690414429
    },
    {
      "run_idx": 40,
      "igd": 0.17188476403460826,
      "hv": 4.173890411813751,
      "n_feasible": 135,
      "time_sec": 1302.8643407821655
    },
    {
      "run_idx": 42,
      "igd": 0.1613865844414644,
      "hv": 4.145875593061652,
      "n_feasible": 135,
      "time_sec": 1062.5456438064575
    },
    {
      "run_idx": 44,
      "igd": 0.1426344936984201,
      "hv": 4.157779894304706,
      "n_feasible": 135,
      "time_sec": 975.1166360378265
    },
    {
      "run_idx": 46,
      "igd": 0.43264458552696694,
      "hv": 2.514376241199449,
      "n_feasible": 135,
      "time_sec": 938.1862595081329
    },
    {
      "run_idx": 49,
      "igd": 0.1501377770932873,
      "hv": 4.174844726065853,
      "n_feasible": 135,
      "time_sec": 898.9356601238251
    },
    {
      "run_idx": 43,
      "igd": 0.15031136431650752,
      "hv": 4.173023467864815,
      "n_feasible": 135,
      "time_sec": 1199.12988114357
    },
    {
      "run_idx": 47,
      "igd": 0.1537307836094729,
      "hv": 4.17279271116306,
      "n_feasible": 135,
      "time_sec": 1259.0612752437592
    },
    {
      "run_idx": 45,
      "igd": 0.14693030467125678,
      "hv": 4.163710799259952,
      "n_feasible": 135,
      "time_sec": 1396.5771033763885
    },
    {
      "run_idx": 50,
      "igd": 0.1436519674030879,
      "hv": 4.127734791589787,
      "n_feasible": 135,
      "time_sec": 1309.024985551834
    },
    {
      "run_idx": 48,
      "igd": 0.1424532039686614,
      "hv": 4.16248752226428,
      "n_feasible": 135,
      "time_sec": 1495.8264849185944
    }
  ]
}