{
  "problem": "DC2DTLZ3",
  "m": 8,
  "algorithm": "CMOEA",
  "igd_median": 0.48553574891281936,
  "igd_iqr": 0.011508535290860877,
  "hv_median": 0.7987354538586048,
  "hv_iqr": 0.09781855871422673,
  "n_runs_feasible": 51,
  "n_runs_total": 51,
  "runs": [
    {
      "run_idx": 0,
      "igd": 0.4884940481971538,
      "hv": 0.7340664658412287,
      "n_feasible": 155,
      "time_sec": 3303.8503930568695
    },
    {
      "run_idx": 1,
      "igd": 0.47918006253848894,
      "hv": 0.8360853285722643,
      "n_feasible": 156,
      "time_sec": 3297.0208168029785
    },
    {
      "run_idx": 2,
      "igd": 0.4854821276043617,
      "hv": 0.7304913223302819,
      "n_feasible": 155,
      "time_sec": 3268.3656256198883
    },
    {
      "run_idx": 8,
      "igd": 0.4949652599669526,
      "hv": 0.7776895543203451,
      "n_feasible": 155,
      "time_sec": 3125.338596343994
    },
    {
      "run_idx": 3,
      "igd": 0.495825822917239,
      "hv": 0.7528712618477063,
      "n_feasible": 155,
      "time_sec": 3293.150135755539
    },
    {
      "run_idx": 9,
      "igd": 0.4844443420377326,
      "hv": 0.818622556828218,
      "n_feasible": 156,
      "time_sec": 3127.9197249412537
    },
    {
      "run_idx": 4,
      "igd": 0.48496900644749136,
      "hv": 0.7566409935396348,
      "n_feasible": 156,
      "time_sec": 3274.7952070236206
    },
    {
      "run_idx": 5,
      "igd": 0.49369789414290777,
      "hv": 0.8979064807327856,
      "n_feasible": 154,
      "time_sec": 3205.7115874290466
    },
    {
      "run_idx": 7,
      "igd": 0.4809861259801834,
      "hv": 0.8518621930940004,
      "n_feasible": 156,
      "time_sec": 3206.3524811267853
    },
    {
      "run_idx": 6,
      "igd": 0.4902974621179343,
      "hv": 0.6661415720582335,
      "n_feasible": 155,
      "time_sec": 3220.1789100170135
    },
    {
      "run_idx": 11,
      "igd": 0.4902541903406517,
      "hv": 0.725711451114087,
      "n_feasible": 156,
      "time_sec": 3121.367936849594
    },
    {
      "run_idx": 10,
      "igd": 0.46527769976032557,
      "hv": 0.8544773714352752,
      "n_feasible": 152,
      "time_sec": 3215.881251811981
    },
    {
      "run_idx": 12,
      "igd": 0.4820684659619041,
      "hv": 0.8153783115478006,
      "n_feasible": 155,
      "time_sec": 2962.008250951767
    },
    {
      "run_idx": 13,
      "igd": 0.47575687048240606,
      "hv": 0.7503787707246178,
      "n_feasible": 154,
      "time_sec": 2994.0990319252014
    },
    {
      "run_idx": 14,
      "igd": 0.4915278837246849,
      "hv": 0.8304263049917316,
      "n_feasible": 154,
      "time_sec": 2991.4362182617188
    },
    {
      "run_idx": 15,
      "igd": 0.49965295578153257,
      "hv": 0.7153230247488419,
      "n_feasible": 155,
      "time_sec": 3106.149486541748
    },
    {
      "run_idx": 16,
      "igd": 0.4885498653126558,
      "hv": 0.7509420319192003,
      "n_feasible": 156,
      "time_sec": 3066.143750667572
    },
    {
      "run_idx": 17,
      "igd": 0.46839678511211785,
      "hv": 0.8261391245067863,
      "n_feasible": 156,
      "time_sec": 3042.3165538311005
    },
    {
      "run_idx": 18,
      "igd": 0.4871338254171006,
      "hv": 0.9101249369498007,
      "n_feasible": 156,
      "time_sec": 3013.533473968506
    },
    {
      "run_idx": 19,
      "igd": 0.4753002326093108,
      "hv": 0.9313893377986536,
      "n_feasible": 154,
      "time_sec": 3017.66246509552
    },
    {
      "run_idx": 23,
      "igd": 0.46647160447478253,
      "hv": 0.8383575835909115,
      "n_feasible": 155,
      "time_sec": 3035.026738166809
    },
    {
      "run_idx": 20,
      "igd": 0.4777822808101713,
      "hv": 0.8608843012656096,
      "n_feasible": 154,
      "time_sec": 3135.7301099300385
    },
    {
      "run_idx": 21,
      "igd": 0.5093273846901004,
      "hv": 0.7128646472177614,
      "n_feasible": 154,
      "time_sec": 3109.2182824611664
    },
    {
      "run_idx": 22,
      "igd": 0.4615752080948564,
      "hv": 0.7994728825715584,
      "n_feasible": 156,
      "time_sec": 3106.0802779197693
    },
    {
      "run_idx": 24,
      "igd": 0.4915413410156602,
      "hv": 0.8901038174613489,
      "n_feasible": 156,
      "time_sec": 3055.0734918117523
    },
    {
      "run_idx": 25,
      "igd": 0.4661092812965477,
      "hv": 0.8530852353283311,
      "n_feasible": 156,
      "time_sec": 3193.1431164741516
    },
    {
      "run_idx": 26,
      "igd": 0.4858456447602571,
      "hv": 0.7130149730781931,
      "n_feasible": 154,
      "time_sec": 3074.3344435691833
    },
    {
      "run_idx": 27,
      "igd": 0.4850689882570803,
      "hv": 0.7987354538586048,
      "n_feasible": 155,
      "time_sec": 3184.9299161434174
    },
    {
      "run_idx": 28,
      "igd": 0.49534280829129784,
      "hv": 0.7506817963299366,
      "n_feasible": 156,
      "time_sec": 3132.7527511119843
    },
    {
      "run_idx": 30,
      "igd": 0.4907924406100603,
      "hv": 0.7253238428589346,
      "n_feasible": 156,
      "time_sec": 3168.6305787563324
    },
    {
      "run_idx": 31,
      "igd": 0.48064955205255555,
      "hv": 0.8925473612456929,
      "n_feasible": 155,
      "time_sec": 3152.378182888031
    },
    {
      "run_idx": 33,
      "igd": 0.49292174134240985,
      "hv": 0.7031819629231362,
      "n_feasible": 155,
      "time_sec": 3147.4210810661316
    },
    {
      "run_idx": 29,
      "igd": 0.488357849284822,
      "hv": 0.8678752276610057,
      "n_feasible": 154,
      "time_sec": 3225.8864798545837
    },
    {
      "run_idx": 34,
      "igd": 0.46773954749141217,
      "hv": 0.841444351348612,
      "n_feasible": 156,
      "time_sec": 3178.104142665863
    },
    {
      "run_idx": 32,
      "igd": 0.49443103669759036,
      "hv": 0.7595353480215393,
      "n_feasible": 156,
      "time_sec": 3216.455965280533
    },
    {
      "run_idx": 38,
      "igd": 0.4807397933172163,
      "hv": 0.8170500344327392,
      "n_feasible": 153,
      "time_sec": 3176.052227497101
    },
    {
      "run_idx": 35,
      "igd": 0.49474935648500445,
      "hv": 0.7560762132358985,
      "n_feasible": 155,
      "time_sec": 3214.1280765533447
    },
    {
      "run_idx": 39,
      "igd": 0.48569910421690793,
      "hv": 0.8075756481923583,
      "n_feasible": 155,
      "time_sec": 3173.218894481659
    },
    {
      "run_idx": 36,
      "igd": 0.4794269883338776,
      "hv": 0.7653482420475154,
      "n_feasible": 155,
      "time_sec": 3210.962954521179
    },
    {
      "run_idx": 41,
      "igd": 0.48062516582474585,
      "hv": 0.8947288691859093,
      "n_feasible": 156,
      "time_sec": 3158.0082828998566
    },
    {
      "run_idx": 37,
      "igd": 0.4833078741172215,
      "hv": 0.7955107466562554,
      "n_feasible": 156,
      "time_sec": 3227.710734128952
    },
    {
      "run_idx": 40,
      "igd": 0.4974475957152117,
      "hv": 0.698399597393605,
      "n_feasible": 154,
      "time_sec": 3216.713410615921
    },
    {
      "run_idx": 43,
      "igd": 0.47401013285698673,
      "hv": 0.7785183511581442,
      "n_feasible": 156,
      "time_sec": 3180.3733835220337
    },
    {
      "run_idx": 42,
      "igd": 0.48749601971845513,
      "hv": 0.8400295828626461,
      "n_feasible": 155,
      "time_sec": 3255.286711215973
    },
    {
      "run_idx": 44,
      "igd": 0.48553574891281936,
      "hv": 0.7199068826540488,
      "n_feasible": 156,
      "time_sec": 3258.8471879959106
    },
    {
      "run_idx": 45,
      "igd": 0.4849854563484075,
      "hv": 0.75029719234331,
      "n_feasible": 156,
      "time_sec": 3179.111124277115
    },
    {
      "run_idx": 46,
      "igd": 0.49376723057091965,
      "hv": 0.8518621930800336,
      "n_feasible": 154,
      "time_sec": 3160.359227180481
    },
    {
      "run_idx": 48,
      "igd": 0.4725777140888923,
      "hv": 0.747372234656882,
      "n_feasible": 155,
      "time_sec": 3035.2440905570984
    },
    {
      "run_idx": 47,
      "igd": 0.4814417633237817,
      "hv": 0.8552490617182308,
      "n_feasible": 153,
      "time_sec": 3099.0098447799683
    },
    {
      "run_idx": 49,
      "igd": 0.4898790337024055,
      "hv": 0.8040601614583646,
      "n_feasible": 156,
      "time_sec": 3003.206909418106
    },
    {
      "run_idx": 50,
      "igd": 0.49250128199414706,
      "hv": 0.7294667245484937,
      "n_feasible": 155,
      "time_sec": 2968.8466172218323
    }
  ]
}